camunda/__init__.py
camunda/client/__init__.py
camunda/client/engine_client.py
camunda/client/external_task_client.py
camunda/client/tests/__init__.py
camunda/client/tests/test_engine_client.py
camunda/client/tests/test_engine_client_auth.py
camunda/client/tests/test_engine_client_bearer.py
camunda/client/tests/test_external_task_client.py
camunda/client/tests/test_external_task_client_auth.py
camunda/client/tests/test_external_task_client_bearer.py
camunda/external_task/__init__.py
camunda/external_task/external_task.py
camunda/external_task/external_task_executor.py
camunda/external_task/external_task_worker.py
camunda/external_task/tests/__init__.py
camunda/external_task/tests/test_external_task.py
camunda/external_task/tests/test_external_task_executor.py
camunda/external_task/tests/test_external_task_worker.py
camunda/process_definition/__init__.py
camunda/process_definition/process_definition_client.py
camunda/process_definition/tests/__init__.py
camunda/process_definition/tests/test_process_definition_client.py
camunda/utils/__init__.py
camunda/utils/auth_basic.py
camunda/utils/auth_bearer.py
camunda/utils/log_utils.py
camunda/utils/response_utils.py
camunda/utils/utils.py
camunda/variables/__init__.py
camunda/variables/properties.py
camunda/variables/variables.py
examples/__init__.py
examples/bpmn_error_example.py
examples/correlate_message.py
examples/event_subprocess_example.py
examples/fetch_and_execute.py
examples/get_process_instance.py
examples/retry_task_example.py
examples/start_process.py
examples/task_handler_example.py
examples/tasks_example.py
examples/examples_auth_basic/__init__.py
examples/examples_auth_basic/fetch_and_execute.py
examples/examples_auth_basic/get_process_instance.py
examples/examples_auth_basic/start_process.py
examples/examples_auth_basic/task_handler_example.py
camunda_external_task_client_python3-4.4.0.dist-info/LICENSE
camunda_external_task_client_python3-4.4.0.dist-info/METADATA
camunda_external_task_client_python3-4.4.0.dist-info/WHEEL
camunda_external_task_client_python3-4.4.0.dist-info/top_level.txt
camunda_external_task_client_python3-4.4.0.dist-info/RECORD
