Metadata-Version: 2.1
Name: camunda-external-task-client-python3
Version: 4.4.0
Summary: Camunda External Task Client for Python 3
Home-page: https://github.com/yogeshrnaik/camunda-external-task-client-python3
Author: Deserve Labs
Author-email: devteam@deserve.com
License: Apache-2.0
Classifier: Intended Audience :: Developers
Classifier: License :: OSI Approved :: Apache Software License
Classifier: Programming Language :: Python :: 3
Classifier: Programming Language :: Python :: 3 :: Only
Classifier: Programming Language :: Python :: 3.7
Classifier: Programming Language :: Python :: 3.8
Classifier: Programming Language :: Python :: 3.9
Classifier: Programming Language :: Python :: 3.10
Classifier: Topic :: Software Development :: Libraries
Requires-Python: >=3.7
License-File: LICENSE
